setup.py
indicatorModule/__init__.py
indicatorModule.egg-info/PKG-INFO
indicatorModule.egg-info/SOURCES.txt
indicatorModule.egg-info/dependency_links.txt
indicatorModule.egg-info/top_level.txt
indicatorModule/backtrader/__init__.py
indicatorModule/backtrader/analyzer.py
indicatorModule/backtrader/broker.py
indicatorModule/backtrader/cerebro.py
indicatorModule/backtrader/comminfo.py
indicatorModule/backtrader/dataseries.py
indicatorModule/backtrader/errors.py
indicatorModule/backtrader/feed.py
indicatorModule/backtrader/fillers.py
indicatorModule/backtrader/flt.py
indicatorModule/backtrader/functions.py
indicatorModule/backtrader/indicator.py
indicatorModule/backtrader/linebuffer.py
indicatorModule/backtrader/lineiterator.py
indicatorModule/backtrader/lineroot.py
indicatorModule/backtrader/lineseries.py
indicatorModule/backtrader/mathsupport.py
indicatorModule/backtrader/metabase.py
indicatorModule/backtrader/observer.py
indicatorModule/backtrader/order.py
indicatorModule/backtrader/position.py
indicatorModule/backtrader/resamplerfilter.py
indicatorModule/backtrader/signal.py
indicatorModule/backtrader/sizer.py
indicatorModule/backtrader/store.py
indicatorModule/backtrader/strategy.py
indicatorModule/backtrader/talib.py
indicatorModule/backtrader/timer.py
indicatorModule/backtrader/trade.py
indicatorModule/backtrader/tradingcal.py
indicatorModule/backtrader/version.py
indicatorModule/backtrader/writer.py
indicatorModule/backtrader/analyzers/__init__.py
indicatorModule/backtrader/analyzers/annualreturn.py
indicatorModule/backtrader/analyzers/calmar.py
indicatorModule/backtrader/analyzers/drawdown.py
indicatorModule/backtrader/analyzers/leverage.py
indicatorModule/backtrader/analyzers/logreturnsrolling.py
indicatorModule/backtrader/analyzers/periodstats.py
indicatorModule/backtrader/analyzers/positions.py
indicatorModule/backtrader/analyzers/pyfolio.py
indicatorModule/backtrader/analyzers/returns.py
indicatorModule/backtrader/analyzers/sharpe.py
indicatorModule/backtrader/analyzers/sqn.py
indicatorModule/backtrader/analyzers/timereturn.py
indicatorModule/backtrader/analyzers/tradeanalyzer.py
