Metadata-Version: 1.0
Name: indicatorModule
Version: 0.0.3
Summary: 量化辅助sdk
Home-page: https://github.com
Author: lw
Author-email: 100000@qq.com
License: UNKNOWN
Platform: UNKNOWN
